ptct/__init__.py
ptct/cli.py
ptct/ptct.py
ptct-0.1.0.dist-info/AUTHORS.rst
ptct-0.1.0.dist-info/LICENSE
ptct-0.1.0.dist-info/METADATA
ptct-0.1.0.dist-info/WHEEL
ptct-0.1.0.dist-info/entry_points.txt
ptct-0.1.0.dist-info/top_level.txt
ptct-0.1.0.dist-info/RECORD
