Metadata-Version: 2.1
Name: ptct
Version: 0.1.0
Summary: Python program to convert temperature between Kelvin, Celsius, Fahrenheit
Home-page: https://github.com/almoore/ptct
Author: Alex Moore
Author-email: alexander.g.moore1@gmail.com
License: Apache Software License 2.0
Keywords: ptct temperature conversion
Platform: UNKNOWN
Classifier: Intended Audience :: Developers
Classifier: License :: OSI Approved :: Apache Software License
Classifier: Natural Language :: English
Classifier: Programming Language :: Python :: 2.7
Classifier: Programming Language :: Python :: 3
Classifier: Programming Language :: Python :: 3.4
Classifier: Programming Language :: Python :: 3.5
Classifier: Programming Language :: Python :: 3.6
Classifier: Programming Language :: Python :: 3.7
